green_migration/__init__.py
green_migration/management/__init__.py
green_migration/management/commands/__init__.py
green_migration/management/commands/green_migrate.py
green_migration/management/commands/pos_green_migrate.py
green_migration/migrations/__init__.py
green_migration/tests/__init__.py
django_green_migration-1.1.2.dist-info/LICENSE
django_green_migration-1.1.2.dist-info/METADATA
django_green_migration-1.1.2.dist-info/WHEEL
django_green_migration-1.1.2.dist-info/top_level.txt
django_green_migration-1.1.2.dist-info/RECORD
