Metadata-Version: 2.1
Name: django-green-migration
Version: 1.1.2
Summary: Generate a green migration files for Django
Author-email: Bang Dao <bang@eoh.io>
License: Apache License
Project-URL: Homepage, https://github.com/eoh-jsc/django-green-migration
Keywords: django,green,migration
Classifier: License :: OSI Approved :: MIT License
Classifier: Programming Language :: Python
Classifier: Programming Language :: Python :: 3
Requires-Python: >=3.7
License-File: LICENSE
Requires-Dist: django >=4.0.0
Provides-Extra: dev
Requires-Dist: pip-tools ; extra == 'dev'
Requires-Dist: pytest ; extra == 'dev'
Requires-Dist: bumpver ; extra == 'dev'
